geonamescache/__init__.py
geonamescache/geonamesdata.py
geonamescache/mappers.py
geonamescache/mappings.py
geonamescache/data/cities1000.json
geonamescache/data/cities15000.json
geonamescache/data/cities500.json
geonamescache/data/cities5000.json
geonamescache/data/continents.json
geonamescache/data/countries.json
geonamescache/data/us_counties.json
geonamescache-1.4.0.dist-info/LICENSE
geonamescache-1.4.0.dist-info/METADATA
geonamescache-1.4.0.dist-info/WHEEL
geonamescache-1.4.0.dist-info/top_level.txt
geonamescache-1.4.0.dist-info/RECORD
